[
  {
    "py/object": "model.contact.Contact",
    "firstname": "",
    "middlename": "",
    "lastname": "",
    "nickname": "",
    "title": "",
    "company": "",
    "address": "",
    "homephone": "",
    "mobilephone": "",
    "workphone": "",
    "fax": "",
    "email": "",
    "secondaryemail": "",
    "thirdemail": "",
    "homepage": "",
    "bday": "",
    "amonth": "-",
    "byear": "",
    "bmonth": "-",
    "aday": "",
    "ayear": "",
    "secondaryaddress": "",
    "secondaryphone": "",
    "notes": "",
    "id": null,
    "all_phones_from_home_page": null,
    "all_email_from_home_page": null
  },
  {
    "py/object": "model.contact.Contact",
    "firstname": "firstnamemt6b>B",
    "middlename": "middlename",
    "lastname": "lastnamek(",
    "nickname": "nicknameH~",
    "title": "title",
    "company": "firstname\"UXE #m`",
    "address": "addressnY-x\\&17B#5}.",
    "homephone": "homephonem",
    "mobilephone": "mobilephone4R",
    "workphone": "workphone:f",
    "fax": "fax",
    "email": "email[|]",
    "secondaryemail": "secondaryemailM}i8s",
    "thirdemail": "thirdemail",
    "homepage": "homepageE3K'",
    "bday": "15",
    "amonth": "August",
    "byear": "3346",
    "bmonth": "February",
    "aday": "5",
    "ayear": "387",
    "secondaryaddress": "secondaryaddress+\"wBr",
    "secondaryphone": "secondaryaddressm \\i/Wu",
    "notes": "notesgRx LE",
    "id": null,
    "all_phones_from_home_page": null,
    "all_email_from_home_page": null
  },
  {
    "py/object": "model.contact.Contact",
    "firstname": "firstnamek",
    "middlename": "middlenamed3:o@e",
    "lastname": "lastnameA",
    "nickname": "nickname6]!{",
    "title": "titleppSC]U\"h5",
    "company": "firstname<N",
    "address": "addressEL*Te_ ",
    "homephone": "homephone",
    "mobilephone": "mobilephone3JA.LN_;1",
    "workphone": "workphonetRfl",
    "fax": "fax'{$fN",
    "email": "email",
    "secondaryemail": "secondaryemail&dJ> ",
    "thirdemail": "thirdemailji,",
    "homepage": "homepage",
    "bday": "30",
    "amonth": "November",
    "byear": "9635",
    "bmonth": "August",
    "aday": "9",
    "ayear": "5361",
    "secondaryaddress": "secondaryaddressJ]vH ",
    "secondaryphone": "secondaryaddressd)%aNM+A2",
    "notes": "notes  Ox-L@b ih2dT",
    "id": null,
    "all_phones_from_home_page": null,
    "all_email_from_home_page": null
  },
  {
    "py/object": "model.contact.Contact",
    "firstname": "firstnameCU\"P}",
    "middlename": "middlenameajtZ!",
    "lastname": "lastname k",
    "nickname": "nickname%d",
    "title": "titleI?JhTI",
    "company": "firstname",
    "address": "addressfH,D~) >rb?",
    "homephone": "homephone8%kvK",
    "mobilephone": "mobilephone7D -",
    "workphone": "workphone",
    "fax": "fax",
    "email": "email^i1",
    "secondaryemail": "secondaryemail",
    "thirdemail": "thirdemailQ8)16",
    "homepage": "homepage",
    "bday": "2",
    "amonth": "February",
    "byear": "3967",
    "bmonth": "February",
    "aday": "19",
    "ayear": "4822",
    "secondaryaddress": "secondaryaddresst6r (",
    "secondaryphone": "secondaryaddress~n>p93",
    "notes": "notes/j{EHNQ_n2) ",
    "id": null,
    "all_phones_from_home_page": null,
    "all_email_from_home_page": null
  },
  {
    "py/object": "model.contact.Contact",
    "firstname": "firstnameNP?&",
    "middlename": "middlenameR",
    "lastname": "lastname.e",
    "nickname": "nickname5SG",
    "title": "title% cZ",
    "company": "firstname>L ",
    "address": "addressq*DLX3ChA$ V-",
    "homephone": "homephone?NPu",
    "mobilephone": "mobilephone9M1B?HGP",
    "workphone": "workphone,W_U=",
    "fax": "fax#6;Q",
    "email": "email",
    "secondaryemail": "secondaryemailQZ,Ib",
    "thirdemail": "thirdemailL",
    "homepage": "homepagez%;",
    "bday": "25",
    "amonth": "August",
    "byear": "5749",
    "bmonth": "September",
    "aday": "4",
    "ayear": "1205",
    "secondaryaddress": "secondaryaddressR';",
    "secondaryphone": "secondaryaddress&",
    "notes": "notesezPv S~SZn A^(~R\\",
    "id": null,
    "all_phones_from_home_page": null,
    "all_email_from_home_page": null
  },
  {
    "py/object": "model.contact.Contact",
    "firstname": "firstnamet",
    "middlename": "middlename",
    "lastname": "lastname' ",
    "nickname": "nicknamenjQ",
    "title": "titleLB o_ux:5",
    "company": "firstnameVx  \"%",
    "address": "addressf1> MXLJp.jnkg",
    "homephone": "homephone2",
    "mobilephone": "mobilephoneLl ~[LT",
    "workphone": "workphone<I~J*",
    "fax": "fax",
    "email": "emailj",
    "secondaryemail": "secondaryemail 0$ ",
    "thirdemail": "thirdemaildMol|",
    "homepage": "homepageua=",
    "bday": "5",
    "amonth": "October",
    "byear": "3446",
    "bmonth": "April",
    "aday": "31",
    "ayear": "2618",
    "secondaryaddress": "secondaryaddress_}",
    "secondaryphone": "secondaryaddressW.i5OAnh",
    "notes": "notes",
    "id": null,
    "all_phones_from_home_page": null,
    "all_email_from_home_page": null
  }
]